zesty/__init__.py
zesty/actions.py
zesty/cloud_vendors.py
zesty/protocol.py
zesty/step_instructions.py
zesty/models/BlockDevice.py
zesty/models/EbsVolume.py
zesty/models/FileSystem.py
zesty/models/InstancesTags.py
zesty/models/ManagedFS.py
zesty/models/Usage.py
zesty/models/agent_report.py
zesty/models/common_base.py
zesty/models/cpu_mon.py
zesty/models/disk_mon.py
zesty/models/hf_interface.py
zesty/models/mem_mon.py
zesty/models/network_mon.py
zesty/models/overview.py
zesty.zbs_api_securonix-1.0.2023.8.29.1693298608.dist-info/METADATA
zesty.zbs_api_securonix-1.0.2023.8.29.1693298608.dist-info/WHEEL
zesty.zbs_api_securonix-1.0.2023.8.29.1693298608.dist-info/top_level.txt
zesty.zbs_api_securonix-1.0.2023.8.29.1693298608.dist-info/RECORD
