Metadata-Version: 2.1
Name: zesty.zbs-api-securonix
Version: 1.0.2023.8.29.1693298608
Summary: Zesty Disk API
Home-page: https://github.com/javatechy/dokr
Author: Zesty.co
Author-email: rnd@cloudvisor.co
License: UNKNOWN
Platform: UNKNOWN
Classifier: Programming Language :: Python :: 3
Classifier: License :: OSI Approved :: MIT License
Classifier: Operating System :: OS Independent
Requires-Dist: requests
Requires-Dist: zesty.zesty-id
